imcpipeline/__init__.py
imcpipeline/_conversion.py
imcpipeline/_version.py
imcpipeline/config.py
imcpipeline/pipeline.py
imcpipeline/runner.py
imcpipeline/utils.py
imcpipeline-0.0.5.dist-info/METADATA
imcpipeline-0.0.5.dist-info/WHEEL
imcpipeline-0.0.5.dist-info/entry_points.txt
imcpipeline-0.0.5.dist-info/top_level.txt
imcpipeline-0.0.5.dist-info/RECORD
