Metadata-Version: 2.1
Name: imcpipeline
Version: 0.0.5
Summary: A pipeline and utils for IMC data analysis.
Home-page: https://github.com/elementolab/imcpipeline
Author: Andre Rendeiro
Author-email: andre.rendeiro@pm.me
License: GPL3
Project-URL: Bug Tracker, https://github.com/elementolab/imcpipeline/issues
Project-URL: Documentation, https://github.com/elementolab/imcpipeline/README.md
Project-URL: Source Code, https://github.com/elementolab/imcpipeline
Keywords: computational biology,bioinformatics,imaging,mass cytometry,mass spectrometry
Platform: UNKNOWN
Classifier: Programming Language :: Python :: 3 :: Only
Classifier: Programming Language :: Python :: 3.7
Classifier: Programming Language :: Python :: 3.8
Classifier: Development Status :: 3 - Alpha
Classifier: Typing :: Typed
Classifier: License :: OSI Approved :: GNU General Public License v3 or later (GPLv3+)
Classifier: Topic :: Scientific/Engineering :: Bio-Informatics
Requires-Dist: requests
Requires-Dist: pandas (>=1.0.1)
Requires-Dist: imctools (==1.0.6)
Requires-Dist: tifffile (==2020.6.3)
Provides-Extra: dev
Requires-Dist: pylint ; extra == 'dev'
Requires-Dist: git-lint ; extra == 'dev'
Requires-Dist: black[d] ; extra == 'dev'
Requires-Dist: mypy ; extra == 'dev'
Requires-Dist: pytest ; extra == 'dev'
Requires-Dist: twine ; extra == 'dev'
